py_mavlink_dji/__init__.py
py_mavlink_dji/adapter.py
py_mavlink_dji/backend.py
py_mavlink_dji/cli.py
py_mavlink_dji/codec.py
py_mavlink_dji/commands.py
py_mavlink_dji/config.py
py_mavlink_dji/missions.py
py_mavlink_dji/state.py
py_mavlink_dji/telemetry.py
py_mavlink_dji/transport.py
py_mavlink_dji-0.0.3.dist-info/METADATA
py_mavlink_dji-0.0.3.dist-info/WHEEL
py_mavlink_dji-0.0.3.dist-info/top_level.txt
py_mavlink_dji-0.0.3.dist-info/RECORD
