Metadata-Version: 2.4
Name: py_mavlink_dji
Version: 0.0.3
Summary: MAVLink to DJI translator bridge (prototype)
Author-email: Auto Generated <dev@example.com>
Classifier: Programming Language :: Python :: 3
Classifier: License :: OSI Approved :: MIT License
Classifier: Operating System :: OS Independent
Requires-Dist: pymavlink
Requires-Dist: pyserial
